app_properties/__init__.py
app_properties/config_handler.py
app_properties/main.py
app_properties/type_converter.py
py_app_properties-1.1.0.dist-info/LICENSE
py_app_properties-1.1.0.dist-info/METADATA
py_app_properties-1.1.0.dist-info/WHEEL
py_app_properties-1.1.0.dist-info/top_level.txt
py_app_properties-1.1.0.dist-info/RECORD
