Metadata-Version: 2.1
Name: py-app-properties
Version: 1.1.0
Summary: Java application properties for Python
Home-page: https://github.com/yar-kik/py-app-properties
Author: Yaroslav Kikvadze
Author-email: yaroslav.k@simporter.com
License: MIT
Classifier: License :: OSI Approved :: MIT License
Classifier: Programming Language :: Python :: 3.8
Classifier: Programming Language :: Python :: 3.9
Classifier: Programming Language :: Python :: 3.10
Requires-Python: >=3.8
License-File: LICENSE
Requires-Dist: PyYAML (>=6.0)
